EasyPlotGUI/__init__.py
EasyPlotGUI-0.1.1.dist-info/LICENSE
EasyPlotGUI-0.1.1.dist-info/METADATA
EasyPlotGUI-0.1.1.dist-info/WHEEL
EasyPlotGUI-0.1.1.dist-info/top_level.txt
EasyPlotGUI-0.1.1.dist-info/RECORD
