Metadata-Version: 2.1
Name: EasyPlotGUI
Version: 0.1.1
Summary: Python library that makes it easy to have a Qt GUI with a matplotlib widget made in QtDesigner implemented on a script.
Home-page: https://github.com/marcelrsoub/EasyPlotGUI
Author: Marcel Soubkovsky
Author-email: marcelclemente.msc@gmail.com
License: GNU
Project-URL: Bug Tracker, https://github.com/marcelrsoub/EasyPlotGUI/issues
Keywords: BPM,FDBPM,SIMULATION,LIGHT PROPAGATION,PHYSICS
Platform: UNKNOWN
Classifier: Development Status :: 3 - Alpha
Classifier: Intended Audience :: Education
Classifier: Topic :: Scientific/Engineering :: Physics
Classifier: License :: OSI Approved :: GNU General Public License (GPL)
Classifier: Programming Language :: Python :: 3
Classifier: Programming Language :: Python :: 3.4
Classifier: Programming Language :: Python :: 3.5
Classifier: Programming Language :: Python :: 3.6
Classifier: Programming Language :: Python :: 3.7
Classifier: Programming Language :: Python :: 3.8
Classifier: Programming Language :: Python :: 3.9
Requires-Python: >=3.6
Requires-Dist: matplotlib (>=3.1PyQt5>=5.13)
